README.txt
setup.py
CherrypyElixir/__init__.py
CherrypyElixir/cherrypy_elixir.py
CherrypyElixir.egg-info/PKG-INFO
CherrypyElixir.egg-info/SOURCES.txt
CherrypyElixir.egg-info/dependency_links.txt
CherrypyElixir.egg-info/requires.txt
CherrypyElixir.egg-info/top_level.txt